apps/arus_demo/app_state.py
apps/arus_demo/backend.py
apps/arus_demo/base.py
apps/arus_demo/components.py
apps/arus_demo/dashboard.py
apps/arus_demo/main.py
apps/arus_demo/session_panel.py
apps/arus_demo/stream_window.py
apps/arus_demo/task_window.py
arus/__init__.py
arus/accelerometer/__init__.py
arus/accelerometer/activation.py
arus/accelerometer/counts.py
arus/accelerometer/extrema.py
arus/accelerometer/orientation.py
arus/accelerometer/spectrum.py
arus/accelerometer/stats.py
arus/class_label.py
arus/cli.py
arus/core/__init__.py
arus/core/pipeline.py
arus/core/tests/__init__.py
arus/core/tests/_test_pipeline.py
arus/dataset/__init__.py
arus/dataset/_process_annotations.py
arus/dataset/_process_mhealth.py
arus/dataset/api.py
arus/dataset/data/actigraph_accel.csv
arus/dataset/data/actigraph_imu.csv
arus/dataset/data_classes.py
arus/developer.py
arus/env.py
arus/error_code.py
arus/extensions/__init__.py
arus/extensions/filesys.py
arus/extensions/joblib.py
arus/extensions/numpy.py
arus/extensions/pandas.py
arus/extensions/plotting.py
arus/extensions/sklearn.py
arus/feature_vector/__init__.py
arus/feature_vector/inertial.py
arus/generator.py
arus/mhealth_format/__init__.py
arus/mhealth_format/constants.py
arus/mhealth_format/core.py
arus/mhealth_format/helper.py
arus/mhealth_format/io.py
arus/models/__init__.py
arus/models/_model.py
arus/models/nn.py
arus/models/prebuilt/intensity.har
arus/models/report.py
arus/models/splitter.py
arus/moment.py
arus/node.py
arus/operator.py
arus/pipeline.py
arus/plugins/__init__.py
arus/plugins/actigraph.py
arus/plugins/metawear.py
arus/plugins/signaligner.py
arus/processor.py
arus/scheduler.py
arus/segmentor.py
arus/spades_lab/__init__.py
arus/spades_lab/annotation.py
arus/spades_lab/placement.py
arus/spades_lab/task_class_map.csv
arus/stream.py
arus/stream2.py
arus/synchronizer.py
arus/testing.py
arus/tests/__init__.py
arus/tests/conftest.py
arus/tests/test_accelerometer.py
arus/tests/test_class_set.py
arus/tests/test_dataset.py
arus-1.1.22.dist-info/entry_points.txt
arus-1.1.22.dist-info/LICENSE.md
arus-1.1.22.dist-info/WHEEL
arus-1.1.22.dist-info/METADATA
arus-1.1.22.dist-info/RECORD
