Metadata-Version: 2.1
Name: arus
Version: 1.1.22
Summary: Activity Recognition with Ubiquitous Sensing
Home-page: https://github.com/qutang/arus
License: GNU
Keywords: ubiquitous computing,activity recognition,sensing,data processing,machine learning
Author: qutang
Author-email: tqshelly@gmail.com
Requires-Python: >=3.7.0,<4.0.0
Classifier: License :: Other/Proprietary License
Classifier: Programming Language :: Python :: 3
Classifier: Programming Language :: Python :: 3.7
Classifier: Programming Language :: Python :: 3.8
Classifier: Programming Language :: Python :: 3.9
Classifier: Topic :: Scientific/Engineering :: Artificial Intelligence
Classifier: Topic :: Scientific/Engineering :: Human Machine Interfaces
Classifier: Topic :: Scientific/Engineering :: Information Analysis
Classifier: Topic :: Software Development :: Libraries :: Python Modules
Provides-Extra: demo
Provides-Extra: dev
Provides-Extra: metawear
Provides-Extra: nn
Requires-Dist: dataclasses (>=0.7,<0.8); python_version >= "3.6" and python_version < "3.7"
Requires-Dist: dephell_versioning (>=0.1.2,<0.2.0); extra == "dev"
Requires-Dist: docopt (>=0.6.2,<0.7.0)
Requires-Dist: joblib (>=1.0.0,<2.0.0)
Requires-Dist: loguru (>=0.5.3,<0.6.0)
Requires-Dist: loky (>=2.6.0,<3.0.0)
Requires-Dist: matplotlib (>=3.1,<4.0)
Requires-Dist: numpy (>=1.19.5,<2.0.0)
Requires-Dist: pandas (>=1.1.5,<2.0.0)
Requires-Dist: pathos (>=0.2.5,<0.3.0)
Requires-Dist: playsound (>=1.2.2,<2.0.0); extra == "demo"
Requires-Dist: pyarrow (>=3.0.0,<4.0.0)
Requires-Dist: pymetawear (>=0.12.0,<0.13.0); extra == "demo" or extra == "metawear"
Requires-Dist: pysimplegui (>=4.14.1,<5.0.0); extra == "demo"
Requires-Dist: scikit-learn (>=0.23.2,<0.24.0)
Requires-Dist: scipy (>=1.3,<2.0)
Requires-Dist: seaborn (>=0.11.0,<0.12.0)
Requires-Dist: semver (>=2.10.1,<3.0.0); extra == "dev"
Requires-Dist: tensorboard (>=2.3.0,<3.0.0); extra == "nn"
Requires-Dist: torch (>=1.6.0,<2.0.0); (sys_platform == "linux") and (extra == "nn")
Requires-Dist: tqdm (>=4.56.0,<5.0.0)
Requires-Dist: tzlocal (>=2.0.0,<3.0.0)
Requires-Dist: wget (>=3.2,<4.0)
Project-URL: Documentation, https://qutang.github.io/arus/
Project-URL: Repository, https://github.com/qutang/arus
